t4gpd/__init__.py
t4gpd/_version.py
t4gpd/avidon/EnergyDemandOfITEquipment.py
t4gpd/avidon/EnergyDemandOfITEquipment2.py
t4gpd/avidon/EnergyDemandOfITEquipment3.py
t4gpd/avidon/STDeploymentOfPVPanels.py
t4gpd/avidon/STDeploymentOfPVPanels2.py
t4gpd/avidon/STDeploymentOfPVPanels3.py
t4gpd/avidon/__init__.py
t4gpd/avidon/commons/AbstractEnergyDemand.py
t4gpd/avidon/commons/EnergyDemandCalculator.py
t4gpd/avidon/commons/EnergyDemandCalculator2.py
t4gpd/avidon/commons/Wh.py
t4gpd/avidon/commons/__init__.py
t4gpd/avidon/scenarios/AbstractScenario.py
t4gpd/avidon/scenarios/CredocBasedScenario.py
t4gpd/avidon/scenarios/FullLockdown.py
t4gpd/avidon/scenarios/__init__.py
t4gpd/comfort/EmpiricalThermalIndices.py
t4gpd/comfort/LinearThermalIndices.py
t4gpd/comfort/UniversalThermalIndices.py
t4gpd/comfort/__init__.py
t4gpd/comfort/algo/CommonsLib.py
t4gpd/comfort/algo/ConstantsLib.py
t4gpd/comfort/algo/ETULib.py
t4gpd/comfort/algo/PETLib.py
t4gpd/comfort/algo/PMVLib.py
t4gpd/comfort/algo/PTLib.py
t4gpd/comfort/algo/SETLib.py
t4gpd/comfort/algo/SET_mist.py
t4gpd/comfort/algo/TmrtGlobeTemperatureLib.py
t4gpd/comfort/algo/TmrtOutLib.py
t4gpd/comfort/algo/UTCILib.py
t4gpd/comfort/algo/VDI_PET_corrected.py
t4gpd/comfort/algo/WindSpeedExtrapolationLib.py
t4gpd/comfort/algo/__init__.py
t4gpd/comfort/indices/ASV.py
t4gpd/comfort/indices/AbstractThermalComfortIndice.py
t4gpd/comfort/indices/DI.py
t4gpd/comfort/indices/ETU.py
t4gpd/comfort/indices/H.py
t4gpd/comfort/indices/HI.py
t4gpd/comfort/indices/NET.py
t4gpd/comfort/indices/OUTSET.py
t4gpd/comfort/indices/PE.py
t4gpd/comfort/indices/PET.py
t4gpd/comfort/indices/PMV.py
t4gpd/comfort/indices/PT.py
t4gpd/comfort/indices/SET.py
t4gpd/comfort/indices/SETmist.py
t4gpd/comfort/indices/THI.py
t4gpd/comfort/indices/TmrtGlobeTemperature.py
t4gpd/comfort/indices/TmrtOut.py
t4gpd/comfort/indices/TmrtRadiometer.py
t4gpd/comfort/indices/UTCI.py
t4gpd/comfort/indices/WCT.py
t4gpd/comfort/indices/__init__.py
t4gpd/commons/AngleLib.py
t4gpd-0.9.8.dist-info/licenses/LICENSE.txt
t4gpd-0.9.8.dist-info/METADATA
t4gpd-0.9.8.dist-info/WHEEL
t4gpd-0.9.8.dist-info/top_level.txt
t4gpd-0.9.8.dist-info/RECORD
