Metadata-Version: 2.4
Name: t4gpd
Version: 0.9.8
Summary: Set of tools based on Python, GeoPandas and Shapely to achieve urban geoprocessing
Home-page: https://t4gpd-docs.readthedocs.io
Download-URL: https://pypi.org/project/t4gpd
Author: Thomas Leduc
Author-email: thomas.leduc@crenau.archi.fr
License: GPLv3+
Keywords: Geospatial analysis,Urban form,Urban morphology,Isovist
Classifier: Development Status :: 4 - Beta
Classifier: Environment :: Console
Classifier: Intended Audience :: Developers
Classifier: Intended Audience :: Education
Classifier: Intended Audience :: End Users/Desktop
Classifier: Intended Audience :: Science/Research
Classifier: License :: OSI Approved :: GNU General Public License v3 or later (GPLv3+)
Classifier: Natural Language :: English
Classifier: Operating System :: OS Independent
Classifier: Programming Language :: Python :: 3
Classifier: Topic :: Education
Classifier: Topic :: Scientific/Engineering :: GIS
Requires-Python: >=3.10
License-File: LICENSE.txt
Dynamic: author
Dynamic: author-email
Dynamic: classifier
Dynamic: description
Dynamic: description-content-type
Dynamic: download-url
Dynamic: home-page
Dynamic: keywords
Dynamic: license
Dynamic: license-file
Dynamic: requires-python
Dynamic: summary
